gen_lazydocs.py
spacetimedb_sdk/__init__.py
spacetimedb_sdk/_version.py
spacetimedb_sdk/client_cache.py
spacetimedb_sdk/local_config.py
spacetimedb_sdk/spacetime_websocket_client.py
spacetimedb_sdk/spacetimedb_async_client.py
spacetimedb_sdk/spacetimedb_client.py
spacetimedb_sdk-0.7.0.dist-info/LICENSE.txt
spacetimedb_sdk-0.7.0.dist-info/METADATA
spacetimedb_sdk-0.7.0.dist-info/WHEEL
spacetimedb_sdk-0.7.0.dist-info/top_level.txt
spacetimedb_sdk-0.7.0.dist-info/RECORD
