Metadata-Version: 2.1
Name: spacetimedb_sdk
Version: 0.7.0
Author-email: Clockwork Labs <john@clockworklabs.io>
Project-URL: homepage, https://spacetimedb.com
Project-URL: repository, https://github.com/clockworklabs/spacetimedb-python-sdk
License-File: LICENSE.txt
Requires-Dist: websocket-client
Requires-Dist: configparser
